kahi_staff_udea_person/Kahi_staff_udea_person.py
kahi_staff_udea_person/__init__.py
kahi_staff_udea_person/_version.py
Kahi_staff_udea_person-0.1.1b0.dist-info/LICENSE
Kahi_staff_udea_person-0.1.1b0.dist-info/METADATA
Kahi_staff_udea_person-0.1.1b0.dist-info/WHEEL
Kahi_staff_udea_person-0.1.1b0.dist-info/top_level.txt
Kahi_staff_udea_person-0.1.1b0.dist-info/RECORD
