Metadata-Version: 2.1
Name: Kahi_staff_udea_person
Version: 0.1.1b0
Summary: Kahi plugin staff_udea_person
Home-page: https://github.com/colav/Kahi_plugins
Author: Colav
Author-email: colav@udea.edu.co
License: BSD
License-File: LICENSE
Requires-Dist: kahi
Requires-Dist: pymongo
Requires-Dist: pandas
Requires-Dist: openpyxl
